systembridgemodels/__init__.py
systembridgemodels/action.py
systembridgemodels/const.py
systembridgemodels/helpers.py
systembridgemodels/keyboard_key.py
systembridgemodels/keyboard_text.py
systembridgemodels/media_control.py
systembridgemodels/media_directories.py
systembridgemodels/media_files.py
systembridgemodels/media_get_file.py
systembridgemodels/media_get_files.py
systembridgemodels/media_play.py
systembridgemodels/notification.py
systembridgemodels/open_path.py
systembridgemodels/open_url.py
systembridgemodels/request.py
systembridgemodels/response.py
systembridgemodels/settings.py
systembridgemodels/update.py
systembridgemodels/fixtures/__init__.py
systembridgemodels/fixtures/media_files.py
systembridgemodels/fixtures/notification.py
systembridgemodels/fixtures/modules/__init__.py
systembridgemodels/fixtures/modules/battery.py
systembridgemodels/fixtures/modules/cpu.py
systembridgemodels/fixtures/modules/disks.py
systembridgemodels/fixtures/modules/displays.py
systembridgemodels/fixtures/modules/gpus.py
systembridgemodels/fixtures/modules/media.py
systembridgemodels/fixtures/modules/memory.py
systembridgemodels/fixtures/modules/networks.py
systembridgemodels/fixtures/modules/processes.py
systembridgemodels/fixtures/modules/sensors.py
systembridgemodels/fixtures/modules/system.py
systembridgemodels/modules/__init__.py
systembridgemodels/modules/battery.py
systembridgemodels/modules/cpu.py
systembridgemodels/modules/disks.py
systembridgemodels/modules/displays.py
systembridgemodels/modules/gpus.py
systembridgemodels/modules/media.py
systembridgemodels/modules/memory.py
systembridgemodels/modules/networks.py
systembridgemodels/modules/processes.py
systembridgemodels/modules/sensors.py
systembridgemodels/modules/system.py
systembridgemodels-5.1.1.dist-info/licenses/LICENSE
systembridgemodels-5.1.1.dist-info/METADATA
systembridgemodels-5.1.1.dist-info/WHEEL
systembridgemodels-5.1.1.dist-info/top_level.txt
systembridgemodels-5.1.1.dist-info/RECORD
