Metadata-Version: 2.4
Name: systembridgemodels
Version: 5.1.1
Summary: System Bridge Models
Home-page: https://github.com/timmo001/system-bridge-models
Author: Aidan Timson (Timmo)
Author-email: aidan@timmo.dev
License: Apache-2.0
Keywords: system-bridge
Requires-Python: >=3.11
License-File: LICENSE
Dynamic: author
Dynamic: author-email
Dynamic: description
Dynamic: description-content-type
Dynamic: home-page
Dynamic: keywords
Dynamic: license
Dynamic: license-file
Dynamic: requires-python
Dynamic: summary
